<?xml version="1.0" encoding="UTF-8"?>
<!DOCTYPE mapper PUBLIC	"-//mybatis.org//DTD Mapper 3.0//EN"
	"http://mybatis.org/dtd/mybatis-3-mapper.dtd">
	
<mapper namespace="kr.co.cc.message.dao.MessageDAO">


	<!-- 보낸 쪽지함 -->
	<select id="sendList" resultType="kr.co.cc.message.dto.MessageDTO">
		SELECT ms.id , ms.to_id , ms.title , ms.send_date , ms.read_chk ,ms.del_chk 
		FROM message ms JOIN member m WHERE ms.from_id = m.id and m.id = #{id} AND ms.del_chk = 0 ORDER BY id DESC 
	</select>
	
	<!-- 받은 쪽지함 -->
	<select id="receiveList" resultType="kr.co.cc.message.dto.MessageDTO">
		SELECT ms.id , ms.from_id , ms.to_id , ms.title , ms.send_date , ms.read_chk ,ms.del_chk 
		FROM message ms JOIN member m WHERE ms.to_id = m.id and m.id = #{id} AND ms.del_chk = 0 ORDER BY id DESC 
	</select>	
	
	<!-- 쪽지 작성 -->
	<insert 
	useGeneratedKeys="true"
	keyColumn="id"
	keyProperty="id"	
	id="msWrite" parameterType="kr.co.cc.message.dto.MessageDTO">
		INSERT INTO message (from_id,to_id,title,content,del_chk,read_chk)	
		values(#{from_id},#{to_id},#{title},#{content},0,0); 		
	</insert>
	
	<!-- 파일 첨부 -->
	<insert id="msfileWrite">
		INSERT INTO attachment(ori_file_name, new_file_name, classification, identify_value)
			VALUES(#{param1}, #{param2}, #{param3}, #{param4})
	</insert>
	
	<!-- 삭제 -->
	<update id="msdelete">
		UPDATE message SET del_chk = 1 WHERE id = #{param1}
	</update>
	
	<!-- 검색 -->
	<select id="search" resultType="kr.co.cc.message.dto.MessageDTO" parameterType="HashMap">
		SELECT * FROM message
			<where>
			<if test="keyword != null and !keyword.equals('') ">
			title LIKE CONCAT('%', #{keyword}, '%')
			</if>
			</where>
	</select>

	<!-- 쪽지 상세보기 -->
	<select id="msdetail" resultType="kr.co.cc.message.dto.MessageDTO">
		SELECT ms.id , ms.from_id ,ms.to_id ,ms.title ,ms.content ,ms.send_date ,ms.del_chk ,ms.read_chk , m1.name, m.dept_name
		FROM message ms
		JOIN member m ON ms.to_id = m.id
		JOIN member m1 ON ms.from_id = m1.id
		WHERE ms.id =#{id}
	</select>	

	<!-- 읽음 처리 -->
	<update id="upHit" parameterType="Integer">
		UPDATE message SET read_chk = 1 WHERE id = #{id}
	</update>	
	
	<select id="msDetailFile">
		SELECT a.new_file_name FROM attachment a 
			INNER JOIN message ms ON ms.id = a.identify_value
		AND a.classification = '쪽지' AND ms.id = #{id}
	</select>
	
</mapper>